<?xml version = '1.0' encoding = 'UTF-8'?>
<Diagram class="oracle.dbtools.crest.swingui.logical.DPVLogical" name="Logical" id="083D86E3-3A90-B891-CFE8-78863B1A00FC">
<createdBy>vickyli</createdBy>
<modifiedBy>vickyli</modifiedBy>
<createdTime>2016-03-22 22:20:51 UTC</createdTime>
<autoRoute>false</autoRoute>
<boxInbox>false</boxInbox>
<showLegend>false</showLegend>
<showLabels>false</showLabels>
<showRelAttributes>false</showRelAttributes>
<gridEnabled>false</gridEnabled>
<showGrid>false</showGrid>
<diagramColor>-1</diagramColor>
<display>false</display>
<notation>2</notation>
<objectViews>
<OView class="oracle.dbtools.crest.swingui.logical.TVEntity" oid="0F77DE3B-1DDB-1CD0-7283-D72101EF28BD" otype="Entity" vid="B03C9988-28CA-6D09-5E90-B8A957C6A251">
<hideElementsInCurrentOnly>false</hideElementsInCurrentOnly>
<bounds x="0" y="333" width="170" height="110"/>
</OView>
<OView class="oracle.dbtools.crest.swingui.logical.TVEntity" oid="22E11669-C102-7F0D-1246-4490DAD769E1" otype="Entity" vid="3273A793-EDE2-4682-242D-334B9203D11B">
<hideElementsInCurrentOnly>false</hideElementsInCurrentOnly>
<bounds x="355" y="127" width="151" height="99"/>
</OView>
<OView class="oracle.dbtools.crest.swingui.logical.TVEntity" oid="476F2788-E379-0CFC-DEDA-996B790246CD" otype="Entity" vid="195F43EB-75FA-88FD-367D-E3F5AB9FC7EA">
<hideElementsInCurrentOnly>false</hideElementsInCurrentOnly>
<bounds x="231" y="316" width="170" height="110"/>
</OView>
<OView class="oracle.dbtools.crest.swingui.logical.TVEntity" oid="58D349BA-ABAD-C53A-8A86-966C9218B7C8" otype="Entity" vid="A0B20C6C-E5F2-8F30-DCA0-53E69AE0B033">
<hideElementsInCurrentOnly>false</hideElementsInCurrentOnly>
<bounds x="560" y="388" width="170" height="110"/>
</OView>
<OView class="oracle.dbtools.crest.swingui.logical.TVEntity" oid="62BB905F-B858-0C3C-9406-1CD59D2E024C" otype="Entity" vid="11575CCF-228B-745D-EBD4-EC69CF78DB87">
<hideElementsInCurrentOnly>false</hideElementsInCurrentOnly>
<bounds x="113" y="105" width="170" height="110"/>
</OView>
<OView class="oracle.dbtools.crest.swingui.logical.TVEntity" oid="66172AB3-704F-0D8E-6E95-B4024E5FF189" otype="Entity" vid="406C48DC-2CB9-AE51-FB96-36DB2002F068">
<hideElementsInCurrentOnly>false</hideElementsInCurrentOnly>
<bounds x="684" y="511" width="165" height="68"/>
</OView>
<OView class="oracle.dbtools.crest.swingui.logical.TVEntity" oid="94084BEB-F4E1-53F7-5FA4-6C0047616D73" otype="Entity" vid="13D4439A-7CD9-906B-BCA8-E7C1A2C287D6">
<hideElementsInCurrentOnly>false</hideElementsInCurrentOnly>
<bounds x="793" y="0" width="170" height="111"/>
</OView>
<OView class="oracle.dbtools.crest.swingui.logical.TVEntity" oid="A5DBC300-2B38-7FE6-8D60-1129691BB601" otype="Entity" vid="4D5A153D-8044-D5D8-9D2B-F64909D2A931">
<hideElementsInCurrentOnly>false</hideElementsInCurrentOnly>
<bounds x="516" y="4" width="170" height="110"/>
</OView>
<OView class="oracle.dbtools.crest.swingui.logical.TVEntity" oid="BCC96F1B-5E01-7DC0-6B89-CBA17FB476C4" otype="Entity" vid="F815EC45-B759-F140-758E-189BEE8A1785">
<hideElementsInCurrentOnly>false</hideElementsInCurrentOnly>
<bounds x="461" y="238" width="170" height="110"/>
</OView>
<OView class="oracle.dbtools.crest.swingui.logical.TVEntity" oid="C8C62A77-18BA-7CCF-1096-DB019C74D684" otype="Entity" vid="6384D50D-2254-1CBC-5007-E82CB56617D3">
<hideElementsInCurrentOnly>false</hideElementsInCurrentOnly>
<bounds x="647" y="135" width="150" height="90"/>
</OView>
<OView class="oracle.dbtools.crest.swingui.logical.TVEntity" oid="DE646A76-3BA3-9D75-DFDB-74EEAD415300" otype="Entity" vid="1B1DD65C-C95B-6162-E6FA-C62AC030E676">
<hideElementsInCurrentOnly>false</hideElementsInCurrentOnly>
<bounds x="463" y="513" width="171" height="67"/>
</OView>
</objectViews>
<connectors>
<Connector class="oracle.dbtools.crest.swingui.logical.TVRelation" oid="147D0040-B83B-6349-8835-71E926D297C4" otype="Relation" vid_source="A0B20C6C-E5F2-8F30-DCA0-53E69AE0B033" vid_target="6384D50D-2254-1CBC-5007-E82CB56617D3">
<hideElementsInCurrentOnly>false</hideElementsInCurrentOnly>
<lineWidth>1</lineWidth>
<points>
<point x="688" y="388"/>
<point x="688" y="225"/>
</points>
</Connector>
<Connector class="oracle.dbtools.crest.swingui.logical.TVInheritanceRelation" oid="18B36FD0-3789-07E2-8A74-87A525CD85A6" otype="Hierarchy relation" vid_source="195F43EB-75FA-88FD-367D-E3F5AB9FC7EA" vid_target="B03C9988-28CA-6D09-5E90-B8A957C6A251">
<hideElementsInCurrentOnly>false</hideElementsInCurrentOnly>
<lineWidth>1</lineWidth>
<points>
<point x="231" y="379"/>
<point x="170" y="379"/>
</points>
</Connector>
<Connector class="oracle.dbtools.crest.swingui.logical.TVRelation" oid="3CF16DB6-1694-EC5C-8CDD-632B827753BC" otype="Relation" vid_source="F815EC45-B759-F140-758E-189BEE8A1785" vid_target="195F43EB-75FA-88FD-367D-E3F5AB9FC7EA">
<hideElementsInCurrentOnly>false</hideElementsInCurrentOnly>
<lineWidth>1</lineWidth>
<points>
<point x="461" y="332"/>
<point x="401" y="332"/>
</points>
</Connector>
<Connector class="oracle.dbtools.crest.swingui.logical.TVInheritanceRelation" oid="45ED2F65-0A15-0FCE-2312-8D0919B479DB" otype="Hierarchy relation" vid_source="A0B20C6C-E5F2-8F30-DCA0-53E69AE0B033" vid_target="406C48DC-2CB9-AE51-FB96-36DB2002F068">
<hideElementsInCurrentOnly>false</hideElementsInCurrentOnly>
<lineWidth>1</lineWidth>
<points>
<point x="707" y="498"/>
<point x="707" y="511"/>
</points>
</Connector>
<Connector class="oracle.dbtools.crest.swingui.logical.TVRelation" oid="4C206A4A-224C-E1F3-736F-5EB1AE65F20D" otype="Relation" vid_source="A0B20C6C-E5F2-8F30-DCA0-53E69AE0B033" vid_target="195F43EB-75FA-88FD-367D-E3F5AB9FC7EA">
<hideElementsInCurrentOnly>false</hideElementsInCurrentOnly>
<lineWidth>1</lineWidth>
<points>
<point x="560" y="407"/>
<point x="401" y="407"/>
</points>
</Connector>
<Connector class="oracle.dbtools.crest.swingui.logical.TVRelation" oid="56FC7722-DE7F-0DC7-163D-F62EDB0588F1" otype="Relation" vid_source="F815EC45-B759-F140-758E-189BEE8A1785" vid_target="A0B20C6C-E5F2-8F30-DCA0-53E69AE0B033">
<hideElementsInCurrentOnly>false</hideElementsInCurrentOnly>
<lineWidth>1</lineWidth>
<points>
<point x="585" y="348"/>
<point x="585" y="388"/>
</points>
</Connector>
<Connector class="oracle.dbtools.crest.swingui.logical.TVRelation" oid="5732BE94-514C-A0CD-06C2-0A00EB926062" otype="Relation" vid_source="F815EC45-B759-F140-758E-189BEE8A1785" vid_target="195F43EB-75FA-88FD-367D-E3F5AB9FC7EA">
<hideElementsInCurrentOnly>false</hideElementsInCurrentOnly>
<lineWidth>1</lineWidth>
<points>
<point x="461" y="342"/>
<point x="401" y="342"/>
</points>
</Connector>
<Connector class="oracle.dbtools.crest.swingui.logical.TVRelation" oid="5ABBE8D3-3AEF-E9AD-3724-3261D999E8CF" otype="Relation" vid_source="A0B20C6C-E5F2-8F30-DCA0-53E69AE0B033" vid_target="6384D50D-2254-1CBC-5007-E82CB56617D3">
<hideElementsInCurrentOnly>false</hideElementsInCurrentOnly>
<lineWidth>1</lineWidth>
<points>
<point x="668" y="388"/>
<point x="668" y="225"/>
</points>
</Connector>
<Connector class="oracle.dbtools.crest.swingui.logical.TVInheritanceRelation" oid="5CFD314C-B65D-F201-E1C0-8387C8487122" otype="Hierarchy relation" vid_source="13D4439A-7CD9-906B-BCA8-E7C1A2C287D6" vid_target="6384D50D-2254-1CBC-5007-E82CB56617D3">
<hideElementsInCurrentOnly>false</hideElementsInCurrentOnly>
<lineWidth>1</lineWidth>
<points>
<point x="795" y="111"/>
<point x="795" y="135"/>
</points>
</Connector>
<Connector class="oracle.dbtools.crest.swingui.logical.TVRelation" oid="6CA28715-9CFD-EFD4-4ED5-F34414C1CA38" otype="Relation" vid_source="13D4439A-7CD9-906B-BCA8-E7C1A2C287D6" vid_target="13D4439A-7CD9-906B-BCA8-E7C1A2C287D6">
<hideElementsInCurrentOnly>false</hideElementsInCurrentOnly>
<lineWidth>1</lineWidth>
<points>
<point x="793" y="62"/>
<point x="767" y="18"/>
<point x="744" y="86"/>
<point x="724" y="110"/>
<point x="794" y="111"/>
</points>
</Connector>
<Connector class="oracle.dbtools.crest.swingui.logical.TVInheritanceRelation" oid="762644E6-182A-21A2-AFD4-7A49E1AC9C54" otype="Hierarchy relation" vid_source="6384D50D-2254-1CBC-5007-E82CB56617D3" vid_target="A0B20C6C-E5F2-8F30-DCA0-53E69AE0B033">
<hideElementsInCurrentOnly>false</hideElementsInCurrentOnly>
<lineWidth>1</lineWidth>
<points>
<point x="698" y="225"/>
<point x="698" y="388"/>
</points>
</Connector>
<Connector class="oracle.dbtools.crest.swingui.logical.TVRelation" oid="77AB6DF8-245C-D10D-C485-9D43BE3B5434" otype="Relation" vid_source="195F43EB-75FA-88FD-367D-E3F5AB9FC7EA" vid_target="195F43EB-75FA-88FD-367D-E3F5AB9FC7EA">
<hideElementsInCurrentOnly>false</hideElementsInCurrentOnly>
<lineWidth>1</lineWidth>
<points>
<point x="231" y="331"/>
<point x="179" y="331"/>
<point x="179" y="411"/>
<point x="174" y="412"/>
<point x="231" y="412"/>
</points>
</Connector>
<Connector class="oracle.dbtools.crest.swingui.logical.TVInheritanceRelation" oid="899B0F02-F183-35A3-C70A-9EEE94994267" otype="Hierarchy relation" vid_source="195F43EB-75FA-88FD-367D-E3F5AB9FC7EA" vid_target="11575CCF-228B-745D-EBD4-EC69CF78DB87">
<hideElementsInCurrentOnly>false</hideElementsInCurrentOnly>
<lineWidth>1</lineWidth>
<points>
<point x="257" y="316"/>
<point x="257" y="215"/>
</points>
</Connector>
<Connector class="oracle.dbtools.crest.swingui.logical.TVRelation" oid="89FE3E7A-BE7B-B0CB-F1CE-CC55E91817B1" otype="Relation" vid_source="13D4439A-7CD9-906B-BCA8-E7C1A2C287D6" vid_target="13D4439A-7CD9-906B-BCA8-E7C1A2C287D6">
<hideElementsInCurrentOnly>false</hideElementsInCurrentOnly>
<lineWidth>1</lineWidth>
<points>
<point x="963" y="69"/>
<point x="1013" y="69"/>
<point x="1013" y="150"/>
<point x="903" y="150"/>
<point x="903" y="111"/>
</points>
</Connector>
<Connector class="oracle.dbtools.crest.swingui.logical.TVInheritanceRelation" oid="96B99C7E-8C64-D010-CF2C-53DB0CA52964" otype="Hierarchy relation" vid_source="13D4439A-7CD9-906B-BCA8-E7C1A2C287D6" vid_target="4D5A153D-8044-D5D8-9D2B-F64909D2A931">
<hideElementsInCurrentOnly>false</hideElementsInCurrentOnly>
<lineWidth>1</lineWidth>
<points>
<point x="793" y="47"/>
<point x="686" y="47"/>
</points>
</Connector>
<Connector class="oracle.dbtools.crest.swingui.logical.TVRelation" oid="AE4584C8-F641-2677-4C2A-7DD0F4AE5F8F" otype="Relation" vid_source="3273A793-EDE2-4682-242D-334B9203D11B" vid_target="11575CCF-228B-745D-EBD4-EC69CF78DB87">
<hideElementsInCurrentOnly>false</hideElementsInCurrentOnly>
<lineWidth>1</lineWidth>
<points>
<point x="355" y="171"/>
<point x="283" y="171"/>
</points>
</Connector>
<Connector class="oracle.dbtools.crest.swingui.logical.TVInheritanceRelation" oid="AFFBF517-3AB8-E275-6017-AA45D0F40859" otype="Hierarchy relation" vid_source="A0B20C6C-E5F2-8F30-DCA0-53E69AE0B033" vid_target="1B1DD65C-C95B-6162-E6FA-C62AC030E676">
<hideElementsInCurrentOnly>false</hideElementsInCurrentOnly>
<lineWidth>1</lineWidth>
<points>
<point x="597" y="498"/>
<point x="597" y="513"/>
</points>
</Connector>
<Connector class="oracle.dbtools.crest.swingui.logical.TVRelation" oid="D660CDF9-AAB3-30B1-400F-ACD068839B6E" otype="Relation" vid_source="F815EC45-B759-F140-758E-189BEE8A1785" vid_target="A0B20C6C-E5F2-8F30-DCA0-53E69AE0B033">
<hideElementsInCurrentOnly>false</hideElementsInCurrentOnly>
<lineWidth>1</lineWidth>
<points>
<point x="595" y="348"/>
<point x="595" y="388"/>
</points>
</Connector>
<Connector class="oracle.dbtools.crest.swingui.logical.TVRelation" oid="DACCB7DB-7539-86CE-D1AD-3D63D1490D6B" otype="Relation" vid_source="A0B20C6C-E5F2-8F30-DCA0-53E69AE0B033" vid_target="195F43EB-75FA-88FD-367D-E3F5AB9FC7EA">
<hideElementsInCurrentOnly>false</hideElementsInCurrentOnly>
<lineWidth>1</lineWidth>
<points>
<point x="560" y="417"/>
<point x="401" y="417"/>
</points>
</Connector>
<Connector class="oracle.dbtools.crest.swingui.logical.TVInheritanceRelation" oid="F6864831-833A-D2A5-EEAC-21C7D44452AA" otype="Hierarchy relation" vid_source="6384D50D-2254-1CBC-5007-E82CB56617D3" vid_target="3273A793-EDE2-4682-242D-334B9203D11B">
<hideElementsInCurrentOnly>false</hideElementsInCurrentOnly>
<lineWidth>1</lineWidth>
<points>
<point x="647" y="180"/>
<point x="506" y="180"/>
</points>
</Connector>
</connectors>
</Diagram>